[
  {
    "german": "der Akkuschrauber",
    "italian": "l'avvitatore"
  },
  {
    "german": "die Rohrzange",
    "italian": "la pinza per tubi"
  },
  {
    "german": "der Winkelschleifer",
    "italian": "la smerigliatrice"
  },
  {
    "german": "die Feile",
    "italian": "la lima"
  },
  {
    "german": "der Zollstock",
    "italian": "il metro pieghevole"
  },
  {
    "german": "der Lötkolben",
    "italian": "il saldatore"
  },
  {
    "german": "das Haargel",
    "italian": "il gel per capelli"
  },
  {
    "german": "die Haarfarbe",
    "italian": "la tintura per capelli"
  },
  {
    "german": "das Rasiermesser",
    "italian": "il rasoio"
  },
  {
    "german": "das Aftershave",
    "italian": "il dopobarba"
  },
  {
    "german": "die Kontaktlinse",
    "italian": "la lente a contatto"
  },
  {
    "german": "die Spüle",
    "italian": "il lavello"
  },
  {
    "german": "die Arbeitsplatte",
    "italian": "il piano di lavoro"
  },
  {
    "german": "die Dunstabzugshaube",
    "italian": "la cappa aspirante"
  },
  {
    "german": "die Fußbodenheizung",
    "italian": "il riscaldamento a pavimento"
  },
  {
    "german": "der Kaminofen",
    "italian": "la stufa a camino"
  },
  {
    "german": "der Schaukelstuhl",
    "italian": "la sedia a dondolo"
  },
  {
    "german": "die Schrankwand",
    "italian": "la parete attrezzata"
  },
  {
    "german": "der Sumpf",
    "italian": "la palude"
  },
  {
    "german": "das Plateau",
    "italian": "l'altopiano"
  },
  {
    "german": "die Steppe",
    "italian": "la steppa"
  },
  {
    "german": "die Tundra",
    "italian": "la tundra"
  },
  {
    "german": "die Meerenge",
    "italian": "lo stretto"
  },
  {
    "german": "die Speise",
    "italian": "la pietanza"
  },
  {
    "german": "die Salatbar",
    "italian": "il buffet insalate"
  },
  {
    "german": "das Gedeck",
    "italian": "il coperto"
  },
  {
    "german": "die Weinkarte",
    "italian": "la carta dei vini"
  },
  {
    "german": "der Sommelier",
    "italian": "il sommelier"
  },
  {
    "german": "der Brunch",
    "italian": "il brunch"
  },
  {
    "german": "die Terrassenplätze",
    "italian": "i posti all'aperto"
  },
  {
    "german": "der Aktenschrank",
    "italian": "l'armadio archivio"
  },
  {
    "german": "die Ablage",
    "italian": "il raccoglitore"
  },
  {
    "german": "der Brieföffner",
    "italian": "il tagliacarte"
  },
  {
    "german": "die Trennwand",
    "italian": "la parete divisoria"
  },
  {
    "german": "das Flipchart",
    "italian": "la lavagna a fogli"
  },
  {
    "german": "der Drehstuhl",
    "italian": "la sedia girevole"
  },
  {
    "german": "unzufrieden",
    "italian": "insoddisfatto"
  },
  {
    "german": "das Oktoberfest",
    "italian": "l'Oktoberfest"
  },
  {
    "german": "der Lebkuchen",
    "italian": "il panpepato"
  },
  {
    "german": "das Sauerkraut",
    "italian": "i crauti"
  },
  {
    "german": "der Kartoffelsalat",
    "italian": "l'insalata di patate"
  },
  {
    "german": "das Dirndl",
    "italian": "il dirndl"
  },
  {
    "german": "die Lederhose",
    "italian": "i pantaloni di pelle"
  },
  {
    "german": "der Schützenfest",
    "italian": "la festa dei tiratori"
  },
  {
    "german": "die Fastnacht",
    "italian": "il carnevale"
  },
  {
    "german": "die Redewendung",
    "italian": "il modo di dire"
  },
  {
    "german": "das Sprichwort",
    "italian": "il proverbio"
  },
  {
    "german": "die Redensart",
    "italian": "l'espressione idiomatica"
  },
  {
    "german": "das Gleichnis",
    "italian": "la parabola"
  },
  {
    "german": "die Moral",
    "italian": "la morale"
  },
  {
    "german": "die Weisheit",
    "italian": "la saggezza"
  },
  {
    "german": "der Aberglaube",
    "italian": "la superstizione"
  },
  {
    "german": "der Brauch",
    "italian": "l'usanza"
  },
  {
    "german": "die Sitte",
    "italian": "il costume"
  },
  {
    "german": "die Tradition",
    "italian": "la tradizione"
  },
  {
    "german": "der Tarif",
    "italian": "la tariffa"
  },
  {
    "german": "die Datenvolumen",
    "italian": "il volume dati"
  },
  {
    "german": "die Grundgebühr",
    "italian": "il canone base"
  },
  {
    "german": "die Mindestvertragslaufzeit",
    "italian": "la durata minima del contratto"
  },
  {
    "german": "die Vertragsverlängerung",
    "italian": "il rinnovo del contratto"
  },
  {
    "german": "die Rufnummernmitnahme",
    "italian": "la portabilità del numero"
  },
  {
    "german": "die Auslandsgebühr",
    "italian": "la tariffa per l'estero"
  },
  {
    "german": "das Datenroaming",
    "italian": "il roaming dati"
  },
  {
    "german": "die Drosselung",
    "italian": "il rallentamento"
  },
  {
    "german": "die Netzabdeckung",
    "italian": "la copertura della rete"
  },
  {
    "german": "die Gesprächsminute",
    "italian": "il minuto di conversazione"
  },
  {
    "german": "die eSIM",
    "italian": "la eSIM"
  },
  {
    "german": "der Stromzähler",
    "italian": "il contatore elettrico"
  },
  {
    "german": "der Gaszähler",
    "italian": "il contatore del gas"
  },
  {
    "german": "der Wasserzähler",
    "italian": "il contatore dell'acqua"
  },
  {
    "german": "die Ablesung",
    "italian": "la lettura del contatore"
  },
  {
    "german": "der Stromversorger",
    "italian": "il fornitore di energia"
  },
  {
    "german": "der Gasversorger",
    "italian": "il fornitore di gas"
  },
  {
    "german": "die Heizungsablesung",
    "italian": "la lettura del riscaldamento"
  },
  {
    "german": "die Gebäudeversicherung",
    "italian": "l'assicurazione sull'edificio"
  },
  {
    "german": "die Straßenreinigung",
    "italian": "la pulizia stradale"
  },
  {
    "german": "die Winterdienstpflicht",
    "italian": "l'obbligo di sgombero neve"
  },
  {
    "german": "der Hausmeisterdienst",
    "italian": "il servizio di custodia"
  },
  {
    "german": "die Treppenhausreinigung",
    "italian": "la pulizia delle scale"
  },
  {
    "german": "die Leggins",
    "italian": "i leggings"
  },
  {
    "german": "die Sohle",
    "italian": "la suola"
  },
  {
    "german": "die Heckenschere",
    "italian": "il tagliasiepi"
  },
  {
    "german": "die Gartenbank",
    "italian": "la panchina da giardino"
  },
  {
    "german": "der Gartenzaun",
    "italian": "la recinzione del giardino"
  },
  {
    "german": "die Vogeltränke",
    "italian": "l'abbeveratoio per uccelli"
  },
  {
    "german": "das Vogelhaus",
    "italian": "la casetta per uccelli"
  },
  {
    "german": "die Blumenerde",
    "italian": "il terriccio"
  },
  {
    "german": "die Unkrautbekämpfung",
    "italian": "la diserbatura"
  },
  {
    "german": "der Mulch",
    "italian": "la pacciamatura"
  },
  {
    "german": "der Welpe",
    "italian": "il cucciolo"
  },
  {
    "german": "das Kätzchen",
    "italian": "il gattino"
  },
  {
    "german": "die Hundehütte",
    "italian": "la cuccia"
  },
  {
    "german": "das Katzenklo",
    "italian": "la lettiera"
  },
  {
    "german": "der Hundeplatz",
    "italian": "l'area cani"
  },
  {
    "german": "die Ecke",
    "italian": "l'angolo"
  },
  {
    "german": "die Unterführung",
    "italian": "il sottopassaggio"
  },
  {
    "german": "die Überführung",
    "italian": "il cavalcavia"
  },
  {
    "german": "der Eisregen",
    "italian": "la pioggia gelata"
  },
  {
    "german": "die Lawine",
    "italian": "la valanga"
  },
  {
    "german": "der Monsun",
    "italian": "il monsone"
  },
  {
    "german": "die Smog",
    "italian": "lo smog"
  },
  {
    "german": "die Inversionswetterlage",
    "italian": "l'inversione termica"
  },
  {
    "german": "der Blues",
    "italian": "il blues"
  },
  {
    "german": "der Rap",
    "italian": "il rap"
  },
  {
    "german": "die Techno-Musik",
    "italian": "la musica techno"
  },
  {
    "german": "der Reggae",
    "italian": "il reggae"
  },
  {
    "german": "das Weihnachten",
    "italian": "il Natale"
  },
  {
    "german": "das Ostern",
    "italian": "la Pasqua"
  },
  {
    "german": "der Karfreitag",
    "italian": "il Venerdì Santo"
  },
  {
    "german": "der Ostermontag",
    "italian": "il Lunedì di Pasqua"
  },
  {
    "german": "der Pfingstmontag",
    "italian": "il Lunedì di Pentecoste"
  },
  {
    "german": "Christi Himmelfahrt",
    "italian": "l'Ascensione"
  },
  {
    "german": "Fronleichnam",
    "italian": "il Corpus Domini"
  },
  {
    "german": "der Reformationstag",
    "italian": "il Giorno della Riforma"
  },
  {
    "german": "Allerheiligen",
    "italian": "Tutti i Santi"
  },
  {
    "german": "der Buß- und Bettag",
    "italian": "il giorno di penitenza e preghiera"
  },
  {
    "german": "der Heiligabend",
    "italian": "la Vigilia di Natale"
  },
  {
    "german": "der Dreikönigstag",
    "italian": "l'Epifania"
  },
  {
    "german": "die Fastenzeit",
    "italian": "la Quaresima"
  },
  {
    "german": "der Advent",
    "italian": "l'Avvento"
  },
  {
    "german": "die Oktave",
    "italian": "l'ottava"
  },
  {
    "german": "die Partitur",
    "italian": "la partitura"
  },
  {
    "german": "das Solo",
    "italian": "l'assolo"
  },
  {
    "german": "das Duo",
    "italian": "il duo"
  },
  {
    "german": "das Trio",
    "italian": "il trio"
  },
  {
    "german": "das Quartett",
    "italian": "il quartetto"
  },
  {
    "german": "der Refrain",
    "italian": "il ritornello"
  },
  {
    "german": "die Telefonkonferenz",
    "italian": "la teleconferenza"
  },
  {
    "german": "die Mittagspause",
    "italian": "la pausa pranzo"
  },
  {
    "german": "die Kaffeepause",
    "italian": "la pausa caffè"
  },
  {
    "german": "die To-do-Liste",
    "italian": "la lista delle cose da fare"
  },
  {
    "german": "das Memo",
    "italian": "il promemoria"
  },
  {
    "german": "der Terminkalender",
    "italian": "l'agenda"
  },
  {
    "german": "die Pendlerstrecke",
    "italian": "il percorso del pendolare"
  },
  {
    "german": "die Kernarbeitszeit",
    "italian": "l'orario di lavoro fisso"
  },
  {
    "german": "der Jahresurlaub",
    "italian": "le ferie annuali"
  },
  {
    "german": "das Taekwondo",
    "italian": "il taekwondo"
  },
  {
    "german": "das Bogenschießen",
    "italian": "il tiro con l'arco"
  },
  {
    "german": "das Gewichtheben",
    "italian": "il sollevamento pesi"
  },
  {
    "german": "das Triathlon",
    "italian": "il triathlon"
  },
  {
    "german": "der Halbmarathon",
    "italian": "la mezza maratona"
  },
  {
    "german": "der Zehnkampf",
    "italian": "il decathlon"
  },
  {
    "german": "die Staffel",
    "italian": "la staffetta"
  },
  {
    "german": "der Hefeteig",
    "italian": "la pasta lievitata"
  },
  {
    "german": "der Mürbeteig",
    "italian": "la pasta frolla"
  },
  {
    "german": "der Blätterteig",
    "italian": "la pasta sfoglia"
  },
  {
    "german": "der Guss",
    "italian": "la copertura"
  },
  {
    "german": "die Springform",
    "italian": "la tortiera apribile"
  },
  {
    "german": "die Rührschüssel",
    "italian": "la ciotola per impastare"
  },
  {
    "german": "der Kuchenrost",
    "italian": "la griglia per dolci"
  },
  {
    "german": "die Silikonform",
    "italian": "lo stampo in silicone"
  },
  {
    "german": "der Wischer",
    "italian": "il mocio"
  },
  {
    "german": "das Fensterputzmittel",
    "italian": "il detergente per vetri"
  },
  {
    "german": "der Staubtuch",
    "italian": "il panno antipolvere"
  },
  {
    "german": "die Sprühflasche",
    "italian": "il flacone spray"
  },
  {
    "german": "die Gummistiefel",
    "italian": "gli stivali di gomma"
  },
  {
    "german": "die Tagessuppe",
    "italian": "la zuppa del giorno"
  },
  {
    "german": "die Windstille",
    "italian": "la bonaccia"
  },
  {
    "german": "die Bewölkung",
    "italian": "la nuvolosità"
  },
  {
    "german": "die Trockenheit",
    "italian": "la siccità"
  },
  {
    "german": "der Tropfen",
    "italian": "la goccia"
  },
  {
    "german": "der Umtausch",
    "italian": "il cambio"
  },
  {
    "german": "die Rückgabe",
    "italian": "la restituzione"
  },
  {
    "german": "der Gutschein",
    "italian": "il buono"
  },
  {
    "german": "die Stoffqualität",
    "italian": "la qualità del tessuto"
  },
  {
    "german": "die Sonderangebot",
    "italian": "l'offerta speciale"
  },
  {
    "german": "dorthin",
    "italian": "là (moto a luogo)"
  },
  {
    "german": "hierher",
    "italian": "qui (moto a luogo)"
  },
  {
    "german": "überall",
    "italian": "ovunque"
  },
  {
    "german": "irgendwo",
    "italian": "da qualche parte"
  },
  {
    "german": "nirgendwo",
    "italian": "da nessuna parte"
  },
  {
    "german": "nirgends",
    "italian": "da nessuna parte"
  },
  {
    "german": "innen",
    "italian": "dentro"
  },
  {
    "german": "außen",
    "italian": "fuori"
  },
  {
    "german": "drinnen",
    "italian": "dentro"
  },
  {
    "german": "draußen",
    "italian": "fuori"
  },
  {
    "german": "nebenan",
    "italian": "accanto"
  },
  {
    "german": "gegenüber",
    "italian": "di fronte"
  },
  {
    "german": "herum",
    "italian": "intorno"
  },
  {
    "german": "vorwärts",
    "italian": "in avanti"
  },
  {
    "german": "rückwärts",
    "italian": "indietro"
  },
  {
    "german": "hin",
    "italian": "verso là"
  },
  {
    "german": "her",
    "italian": "verso qui"
  },
  {
    "german": "hinein",
    "italian": "dentro"
  },
  {
    "german": "heraus",
    "italian": "fuori"
  },
  {
    "german": "hinauf",
    "italian": "su"
  },
  {
    "german": "hinunter",
    "italian": "giù"
  },
  {
    "german": "lieber",
    "italian": "preferibilmente"
  },
  {
    "german": "am liebsten",
    "italian": "soprattutto"
  },
  {
    "german": "anders",
    "italian": "diversamente"
  },
  {
    "german": "genauso",
    "italian": "altrettanto"
  },
  {
    "german": "extra",
    "italian": "apposta"
  },
  {
    "german": "zufällig",
    "italian": "per caso"
  },
  {
    "german": "automatisch",
    "italian": "automaticamente"
  },
  {
    "german": "öffentlich",
    "italian": "pubblicamente"
  },
  {
    "german": "privat",
    "italian": "privatamente"
  },
  {
    "german": "persönlich",
    "italian": "personalmente"
  },
  {
    "german": "direkt",
    "italian": "direttamente"
  },
  {
    "german": "erfolgreich",
    "italian": "con successo"
  },
  {
    "german": "kaum",
    "italian": "a malapena"
  },
  {
    "german": "völlig",
    "italian": "completamente"
  },
  {
    "german": "besonders",
    "italian": "particolarmente"
  },
  {
    "german": "unglaublich",
    "italian": "incredibilmente"
  },
  {
    "german": "eigentlich",
    "italian": "in realtà"
  },
  {
    "german": "etwa",
    "italian": "circa"
  },
  {
    "german": "ungefähr",
    "italian": "circa"
  },
  {
    "german": "circa",
    "italian": "circa"
  },
  {
    "german": "bestimmt",
    "italian": "sicuramente"
  },
  {
    "german": "wahrscheinlich",
    "italian": "probabilmente"
  },
  {
    "german": "hoffentlich",
    "italian": "speriamo"
  },
  {
    "german": "überhaupt",
    "italian": "in generale"
  },
  {
    "german": "doch",
    "italian": "però"
  },
  {
    "german": "sondern",
    "italian": "bensì"
  },
  {
    "german": "deshalb",
    "italian": "perciò"
  },
  {
    "german": "deswegen",
    "italian": "per questo"
  },
  {
    "german": "darum",
    "italian": "per questo"
  },
  {
    "german": "trotzdem",
    "italian": "tuttavia"
  },
  {
    "german": "außerdem",
    "italian": "inoltre"
  },
  {
    "german": "sonst",
    "italian": "altrimenti"
  },
  {
    "german": "entweder...oder",
    "italian": "o...o"
  },
  {
    "german": "weder...noch",
    "italian": "né...né"
  },
  {
    "german": "übrigens",
    "italian": "tra l'altro"
  },
  {
    "german": "nämlich",
    "italian": "infatti"
  },
  {
    "german": "um ... zu",
    "italian": "per"
  },
  {
    "german": "entweder ... oder",
    "italian": "o ... o"
  },
  {
    "german": "obwohl",
    "italian": "nonostante"
  },
  {
    "german": "während",
    "italian": "mentre"
  },
  {
    "german": "bevor",
    "italian": "prima che"
  },
  {
    "german": "nachdem",
    "italian": "dopo che"
  },
  {
    "german": "damit",
    "italian": "affinché"
  },
  {
    "german": "um...zu",
    "italian": "per"
  },
  {
    "german": "ohne...zu",
    "italian": "senza"
  },
  {
    "german": "wegen",
    "italian": "a causa di"
  },
  {
    "german": "außer",
    "italian": "eccetto"
  },
  {
    "german": "eine Milliarde",
    "italian": "un miliardo"
  },
  {
    "german": "ein Drittel",
    "italian": "un terzo"
  },
  {
    "german": "dreifach",
    "italian": "triplo"
  },
  {
    "german": "der Schwiegervater",
    "italian": "il suocero"
  },
  {
    "german": "die Schwiegermutter",
    "italian": "la suocera"
  },
  {
    "german": "der Schwager",
    "italian": "il cognato"
  },
  {
    "german": "die Schwägerin",
    "italian": "la cognata"
  },
  {
    "german": "der Schwiegersohn",
    "italian": "il genero"
  },
  {
    "german": "die Schwiegertochter",
    "italian": "la nuora"
  },
  {
    "german": "der Stiefvater",
    "italian": "il patrigno"
  },
  {
    "german": "die Stiefmutter",
    "italian": "la matrigna"
  },
  {
    "german": "der Halbbruder",
    "italian": "il fratellastro"
  },
  {
    "german": "die Halbschwester",
    "italian": "la sorellastra"
  },
  {
    "german": "ledig",
    "italian": "celibe/nubile"
  },
  {
    "german": "geschieden",
    "italian": "divorziato"
  },
  {
    "german": "verwitwet",
    "italian": "vedovo"
  },
  {
    "german": "der Jugendliche",
    "italian": "l'adolescente"
  },
  {
    "german": "der Rentner",
    "italian": "il pensionato"
  },
  {
    "german": "die Scheidung",
    "italian": "il divorzio"
  },
  {
    "german": "die Grenze",
    "italian": "il limite"
  },
  {
    "german": "das Hochhaus",
    "italian": "il grattacielo"
  },
  {
    "german": "die Villa",
    "italian": "la villa"
  },
  {
    "german": "das Schloss",
    "italian": "il castello"
  },
  {
    "german": "das Ferienhaus",
    "italian": "la casa vacanze"
  },
  {
    "german": "die Ferienwohnung",
    "italian": "l'appartamento vacanze"
  },
  {
    "german": "das Arbeitszimmer",
    "italian": "lo studio"
  },
  {
    "german": "das Gästezimmer",
    "italian": "la camera degli ospiti"
  },
  {
    "german": "das Esszimmer",
    "italian": "la sala da pranzo"
  },
  {
    "german": "der Flur",
    "italian": "il corridoio"
  },
  {
    "german": "der Gang",
    "italian": "il corridoio"
  },
  {
    "german": "der Keller",
    "italian": "la cantina"
  },
  {
    "german": "das Erdgeschoss",
    "italian": "il piano terra"
  },
  {
    "german": "der erste Stock",
    "italian": "il primo piano"
  },
  {
    "german": "die Etage",
    "italian": "il piano"
  },
  {
    "german": "das Stockwerk",
    "italian": "il piano"
  },
  {
    "german": "die Terrasse",
    "italian": "la terrazza"
  },
  {
    "german": "der Hof",
    "italian": "il cortile"
  },
  {
    "german": "der Parkplatz",
    "italian": "il parcheggio"
  },
  {
    "german": "die Haustür",
    "italian": "la porta d'ingresso"
  },
  {
    "german": "die Stufe",
    "italian": "il gradino"
  },
  {
    "german": "die Heizung",
    "italian": "il riscaldamento"
  },
  {
    "german": "die Klimaanlage",
    "italian": "l'aria condizionata"
  },
  {
    "german": "die Steckdose",
    "italian": "la presa elettrica"
  },
  {
    "german": "der Lichtschalter",
    "italian": "l'interruttore"
  },
  {
    "german": "die Klingel",
    "italian": "il campanello"
  },
  {
    "german": "der Briefkasten",
    "italian": "la cassetta delle lettere"
  },
  {
    "german": "der Esstisch",
    "italian": "il tavolo da pranzo"
  },
  {
    "german": "der Couchtisch",
    "italian": "il tavolino"
  },
  {
    "german": "der Nachttisch",
    "italian": "il comodino"
  },
  {
    "german": "der Sessel",
    "italian": "la poltrona"
  },
  {
    "german": "die Bank",
    "italian": "la panchina"
  },
  {
    "german": "das Einzelbett",
    "italian": "il letto singolo"
  },
  {
    "german": "das Doppelbett",
    "italian": "il letto matrimoniale"
  },
  {
    "german": "das Kinderbett",
    "italian": "il lettino"
  },
  {
    "german": "die Matratze",
    "italian": "il materasso"
  },
  {
    "german": "das Kissen",
    "italian": "il cuscino"
  },
  {
    "german": "der Kleiderschrank",
    "italian": "l'armadio per vestiti"
  },
  {
    "german": "das Regal",
    "italian": "lo scaffale"
  },
  {
    "german": "das Bücherregal",
    "italian": "la libreria"
  },
  {
    "german": "die Schublade",
    "italian": "il cassetto"
  },
  {
    "german": "der Teppich",
    "italian": "il tappeto"
  },
  {
    "german": "die Vase",
    "italian": "il vaso"
  },
  {
    "german": "der Gefrierschrank",
    "italian": "il congelatore"
  },
  {
    "german": "die Mikrowelle",
    "italian": "il microonde"
  },
  {
    "german": "der Toaster",
    "italian": "il tostapane"
  },
  {
    "german": "die Kaffeemaschine",
    "italian": "la macchina del caffè"
  },
  {
    "german": "der Wasserkocher",
    "italian": "il bollitore"
  },
  {
    "german": "der Mixer",
    "italian": "il frullatore"
  },
  {
    "german": "der Geschirrspüler",
    "italian": "la lavastoviglie"
  },
  {
    "german": "die Spülmaschine",
    "italian": "la lavastoviglie"
  },
  {
    "german": "der Trockner",
    "italian": "l'asciugatrice"
  },
  {
    "german": "das Bügeleisen",
    "italian": "il ferro da stiro"
  },
  {
    "german": "der Staubsauger",
    "italian": "l'aspirapolvere"
  },
  {
    "german": "der Besen",
    "italian": "la scopa"
  },
  {
    "german": "der Eimer",
    "italian": "il secchio"
  },
  {
    "german": "der Deckel",
    "italian": "il coperchio"
  },
  {
    "german": "das Schneidebrett",
    "italian": "il tagliere"
  },
  {
    "german": "das Küchenmesser",
    "italian": "il coltello da cucina"
  },
  {
    "german": "der Teelöffel",
    "italian": "il cucchiaino"
  },
  {
    "german": "der Esslöffel",
    "italian": "il cucchiaio da tavola"
  },
  {
    "german": "das Besteck",
    "italian": "le posate"
  },
  {
    "german": "der Dosenöffner",
    "italian": "l'apriscatole"
  },
  {
    "german": "der Flaschenöffner",
    "italian": "l'apribottiglie"
  },
  {
    "german": "die Schere",
    "italian": "le forbici"
  },
  {
    "german": "die Schüssel",
    "italian": "la ciotola"
  },
  {
    "german": "die Kanne",
    "italian": "la caraffa"
  },
  {
    "german": "die Teekanne",
    "italian": "la teiera"
  },
  {
    "german": "die Kaffeekanne",
    "italian": "la caffettiera"
  },
  {
    "german": "die Serviette",
    "italian": "il tovagliolo"
  },
  {
    "german": "die Tischdecke",
    "italian": "la tovaglia"
  },
  {
    "german": "die Backform",
    "italian": "lo stampo"
  },
  {
    "german": "das Brotmesser",
    "italian": "il coltello per il pane"
  },
  {
    "german": "der Kochlöffel",
    "italian": "il mestolo"
  },
  {
    "german": "die Kelle",
    "italian": "il mestolo"
  },
  {
    "german": "das Weinglas",
    "italian": "il calice"
  },
  {
    "german": "die Badewanne",
    "italian": "la vasca da bagno"
  },
  {
    "german": "der Wasserhahn",
    "italian": "il rubinetto"
  },
  {
    "german": "das Toilettenpapier",
    "italian": "la carta igienica"
  },
  {
    "german": "das Duschgel",
    "italian": "il bagnoschiuma"
  },
  {
    "german": "der Rasierapparat",
    "italian": "il rasoio"
  },
  {
    "german": "der Rasierer",
    "italian": "il rasoio"
  },
  {
    "german": "der Föhn",
    "italian": "il phon"
  },
  {
    "german": "die Bürste",
    "italian": "la spazzola"
  },
  {
    "german": "der Kamm",
    "italian": "il pettine"
  },
  {
    "german": "das Deo",
    "italian": "il deodorante"
  },
  {
    "german": "das Parfüm",
    "italian": "il profumo"
  },
  {
    "german": "die Creme",
    "italian": "la crema"
  },
  {
    "german": "die Waage",
    "italian": "la bilancia"
  },
  {
    "german": "das Mehl",
    "italian": "la farina"
  },
  {
    "german": "der Pfeffer",
    "italian": "il pepe"
  },
  {
    "german": "das Olivenöl",
    "italian": "l'olio d'oliva"
  },
  {
    "german": "die Sahne",
    "italian": "la panna"
  },
  {
    "german": "der Parmesan",
    "italian": "il parmigiano"
  },
  {
    "german": "der Mozzarella",
    "italian": "la mozzarella"
  },
  {
    "german": "das Rindfleisch",
    "italian": "la carne di manzo"
  },
  {
    "german": "das Schweinefleisch",
    "italian": "la carne di maiale"
  },
  {
    "german": "die Pute",
    "italian": "il tacchino"
  },
  {
    "german": "das Lamm",
    "italian": "l'agnello"
  },
  {
    "german": "das Hackfleisch",
    "italian": "la carne macinata"
  },
  {
    "german": "der Schinken",
    "italian": "il prosciutto"
  },
  {
    "german": "der Speck",
    "italian": "la pancetta"
  },
  {
    "german": "der Lachs",
    "italian": "il salmone"
  },
  {
    "german": "der Thunfisch",
    "italian": "il tonno"
  },
  {
    "german": "die Bohne",
    "italian": "il fagiolo"
  },
  {
    "german": "die Erbse",
    "italian": "il pisello"
  },
  {
    "german": "der Essig",
    "italian": "l'aceto"
  },
  {
    "german": "der Senf",
    "italian": "la senape"
  },
  {
    "german": "die Mayonnaise",
    "italian": "la maionese"
  },
  {
    "german": "die Soße",
    "italian": "la salsa"
  },
  {
    "german": "die Brühe",
    "italian": "il brodo"
  },
  {
    "german": "der Honig",
    "italian": "il miele"
  },
  {
    "german": "die Marmelade",
    "italian": "la marmellata"
  },
  {
    "german": "die Semmel",
    "italian": "il panino"
  },
  {
    "german": "die Himbeere",
    "italian": "il lampone"
  },
  {
    "german": "die Heidelbeere",
    "italian": "il mirtillo"
  },
  {
    "german": "die Kirsche",
    "italian": "la ciliegia"
  },
  {
    "german": "der Pfirsich",
    "italian": "la pesca"
  },
  {
    "german": "die Aprikose",
    "italian": "l'albicocca"
  },
  {
    "german": "die Pflaume",
    "italian": "la prugna"
  },
  {
    "german": "die Melone",
    "italian": "il melone"
  },
  {
    "german": "die Wassermelone",
    "italian": "l'anguria"
  },
  {
    "german": "die Ananas",
    "italian": "l'ananas"
  },
  {
    "german": "die Mango",
    "italian": "il mango"
  },
  {
    "german": "die Kiwi",
    "italian": "il kiwi"
  },
  {
    "german": "die Avocado",
    "italian": "l'avocado"
  },
  {
    "german": "die Kokosnuss",
    "italian": "la noce di cocco"
  },
  {
    "german": "die Paprika",
    "italian": "il peperone"
  },
  {
    "german": "der Knoblauch",
    "italian": "l'aglio"
  },
  {
    "german": "der Spinat",
    "italian": "gli spinaci"
  },
  {
    "german": "der Kohl",
    "italian": "il cavolo"
  },
  {
    "german": "der Blumenkohl",
    "italian": "il cavolfiore"
  },
  {
    "german": "der Brokkoli",
    "italian": "i broccoli"
  },
  {
    "german": "die Zucchini",
    "italian": "la zucchina"
  },
  {
    "german": "die Aubergine",
    "italian": "la melanzana"
  },
  {
    "german": "der Kürbis",
    "italian": "la zucca"
  },
  {
    "german": "der Champignon",
    "italian": "il fungo champignon"
  },
  {
    "german": "der Pilz",
    "italian": "il fungo"
  },
  {
    "german": "der Mais",
    "italian": "il mais"
  },
  {
    "german": "die Olive",
    "italian": "l'oliva"
  },
  {
    "german": "die Nuss",
    "italian": "la noce"
  },
  {
    "german": "die Walnuss",
    "italian": "la noce"
  },
  {
    "german": "die Haselnuss",
    "italian": "la nocciola"
  },
  {
    "german": "die Mandel",
    "italian": "la mandorla"
  },
  {
    "german": "die Erdnuss",
    "italian": "l'arachide"
  },
  {
    "german": "das Gewürz",
    "italian": "la spezia"
  },
  {
    "german": "das Basilikum",
    "italian": "il basilico"
  },
  {
    "german": "die Petersilie",
    "italian": "il prezzemolo"
  },
  {
    "german": "die Minze",
    "italian": "la menta"
  },
  {
    "german": "der Rosmarin",
    "italian": "il rosmarino"
  },
  {
    "german": "der Oregano",
    "italian": "l'origano"
  },
  {
    "german": "der Zimt",
    "italian": "la cannella"
  },
  {
    "german": "die Vanille",
    "italian": "la vaniglia"
  },
  {
    "german": "der Ingwer",
    "italian": "lo zenzero"
  },
  {
    "german": "der Paprika",
    "italian": "la paprika"
  },
  {
    "german": "der Curry",
    "italian": "il curry"
  },
  {
    "german": "die Chilischote",
    "italian": "il peperoncino"
  },
  {
    "german": "die Gewürze",
    "italian": "le spezie"
  },
  {
    "german": "die Kräuter",
    "italian": "le erbe aromatiche"
  },
  {
    "german": "der Basilikum",
    "italian": "il basilico"
  },
  {
    "german": "der Chili",
    "italian": "il peperoncino"
  },
  {
    "german": "die Sojasauce",
    "italian": "la salsa di soia"
  },
  {
    "german": "das Pesto",
    "italian": "il pesto"
  },
  {
    "german": "würzen",
    "italian": "condire"
  },
  {
    "german": "schälen",
    "italian": "sbucciare"
  },
  {
    "german": "mixen",
    "italian": "mixare"
  },
  {
    "german": "umrühren",
    "italian": "rimescolare"
  },
  {
    "german": "aufwärmen",
    "italian": "riscaldare"
  },
  {
    "german": "einfrieren",
    "italian": "congelare"
  },
  {
    "german": "servieren",
    "italian": "servire"
  },
  {
    "german": "das Rezept",
    "italian": "la ricetta"
  },
  {
    "german": "die Zutat",
    "italian": "l'ingrediente"
  },
  {
    "german": "die Portion",
    "italian": "la porzione"
  },
  {
    "german": "roh",
    "italian": "crudo"
  },
  {
    "german": "gekocht",
    "italian": "cotto"
  },
  {
    "german": "gebraten",
    "italian": "fritto"
  },
  {
    "german": "wenden",
    "italian": "girare"
  },
  {
    "german": "der Snack",
    "italian": "lo spuntino"
  },
  {
    "german": "die Vorspeise",
    "italian": "l'antipasto"
  },
  {
    "german": "die Hauptspeise",
    "italian": "il piatto principale"
  },
  {
    "german": "die Beilage",
    "italian": "il contorno"
  },
  {
    "german": "der Nachtisch",
    "italian": "il dolce"
  },
  {
    "german": "das Dessert",
    "italian": "il dessert"
  },
  {
    "german": "der Braten",
    "italian": "l'arrosto"
  },
  {
    "german": "das Schnitzel",
    "italian": "la cotoletta"
  },
  {
    "german": "das Steak",
    "italian": "la bistecca"
  },
  {
    "german": "das Omelett",
    "italian": "la frittata"
  },
  {
    "german": "der Pfannkuchen",
    "italian": "la crepe"
  },
  {
    "german": "die Torte",
    "italian": "la torta"
  },
  {
    "german": "das Bonbon",
    "italian": "la caramella"
  },
  {
    "german": "die Medien",
    "italian": "i media"
  },
  {
    "german": "die Zeitschrift",
    "italian": "la rivista"
  },
  {
    "german": "das Magazin",
    "italian": "il magazine"
  },
  {
    "german": "der Journalist",
    "italian": "il giornalista"
  },
  {
    "german": "die Journalistin",
    "italian": "la giornalista"
  },
  {
    "german": "der Artikel",
    "italian": "l'articolo"
  },
  {
    "german": "der Bericht",
    "italian": "il rapporto"
  },
  {
    "german": "berichten",
    "italian": "riferire"
  },
  {
    "german": "melden",
    "italian": "segnalare"
  },
  {
    "german": "der Kommentar",
    "italian": "il commento"
  },
  {
    "german": "das Interview",
    "italian": "l'intervista"
  },
  {
    "german": "der Sender",
    "italian": "l'emittente"
  },
  {
    "german": "senden",
    "italian": "trasmettere"
  },
  {
    "german": "die Sendung",
    "italian": "la trasmissione"
  },
  {
    "german": "die Fernsehsendung",
    "italian": "il programma TV"
  },
  {
    "german": "der Fernsehsender",
    "italian": "il canale TV"
  },
  {
    "german": "der Kanal",
    "italian": "il canale"
  },
  {
    "german": "die Talkshow",
    "italian": "il talk show"
  },
  {
    "german": "der Moderator",
    "italian": "il conduttore"
  },
  {
    "german": "die Moderatorin",
    "italian": "la conduttrice"
  },
  {
    "german": "live",
    "italian": "in diretta"
  },
  {
    "german": "offline",
    "italian": "offline"
  },
  {
    "german": "die Webseite",
    "italian": "il sito web"
  },
  {
    "german": "die Website",
    "italian": "il sito web"
  },
  {
    "german": "die Homepage",
    "italian": "la homepage"
  },
  {
    "german": "der Blog",
    "italian": "il blog"
  },
  {
    "german": "der Post",
    "italian": "il post"
  },
  {
    "german": "posten",
    "italian": "postare"
  },
  {
    "german": "liken",
    "italian": "mettere like"
  },
  {
    "german": "der Like",
    "italian": "il like"
  },
  {
    "german": "mailen",
    "italian": "inviare email"
  },
  {
    "german": "die Chat-Nachricht",
    "italian": "il messaggio chat"
  },
  {
    "german": "chatten",
    "italian": "chattare"
  },
  {
    "german": "der Chat",
    "italian": "la chat"
  },
  {
    "german": "herunterladen",
    "italian": "scaricare"
  },
  {
    "german": "der Download",
    "italian": "il download"
  },
  {
    "german": "der Upload",
    "italian": "l'upload"
  },
  {
    "german": "der Account",
    "italian": "l'account"
  },
  {
    "german": "das Profil",
    "italian": "il profilo"
  },
  {
    "german": "einloggen",
    "italian": "accedere"
  },
  {
    "german": "ausloggen",
    "italian": "disconnettersi"
  },
  {
    "german": "der Benutzername",
    "italian": "il nome utente"
  },
  {
    "german": "der Link",
    "italian": "il link"
  },
  {
    "german": "klicken",
    "italian": "cliccare"
  },
  {
    "german": "die Rede",
    "italian": "il discorso"
  },
  {
    "german": "sich unterhalten",
    "italian": "conversare"
  },
  {
    "german": "die Unterhaltung",
    "italian": "la conversazione"
  },
  {
    "german": "diskutieren",
    "italian": "discutere"
  },
  {
    "german": "die Diskussion",
    "italian": "la discussione"
  },
  {
    "german": "das Argument",
    "italian": "l'argomento"
  },
  {
    "german": "überzeugen",
    "italian": "convincere"
  },
  {
    "german": "beschreiben",
    "italian": "descrivere"
  },
  {
    "german": "informieren",
    "italian": "informare"
  },
  {
    "german": "ausdrücken",
    "italian": "esprimere"
  },
  {
    "german": "aussprechen",
    "italian": "pronunciare"
  },
  {
    "german": "die Aussprache",
    "italian": "la pronuncia"
  },
  {
    "german": "verraten",
    "italian": "rivelare"
  },
  {
    "german": "das Geheimnis",
    "italian": "il segreto"
  },
  {
    "german": "geheim",
    "italian": "segreto"
  },
  {
    "german": "schreien",
    "italian": "gridare"
  },
  {
    "german": "der Schrei",
    "italian": "il grido"
  },
  {
    "german": "der Dialog",
    "italian": "il dialogo"
  },
  {
    "german": "der Vortrag",
    "italian": "la conferenza"
  },
  {
    "german": "die Neuigkeit",
    "italian": "la novità"
  },
  {
    "german": "der Tipp",
    "italian": "il consiglio"
  },
  {
    "german": "die Anfrage",
    "italian": "la richiesta"
  },
  {
    "german": "die Bitte",
    "italian": "la richiesta"
  },
  {
    "german": "die Erlaubnis",
    "italian": "il permesso"
  },
  {
    "german": "das Verbot",
    "italian": "il divieto"
  },
  {
    "german": "die Warnung",
    "italian": "l'avvertimento"
  },
  {
    "german": "das Versprechen",
    "italian": "la promessa"
  },
  {
    "german": "der Dank",
    "italian": "il ringraziamento"
  },
  {
    "german": "die Begrüßung",
    "italian": "il saluto"
  },
  {
    "german": "der Abschied",
    "italian": "l'addio"
  },
  {
    "german": "die Einladung",
    "italian": "l'invito"
  },
  {
    "german": "die Glückwünsche",
    "italian": "gli auguri"
  },
  {
    "german": "die Werbung",
    "italian": "la pubblicità"
  },
  {
    "german": "werben",
    "italian": "pubblicizzare"
  },
  {
    "german": "das Plakat",
    "italian": "il manifesto"
  },
  {
    "german": "der Flyer",
    "italian": "il volantino"
  },
  {
    "german": "der Katalog",
    "italian": "il catalogo"
  },
  {
    "german": "die Marke",
    "italian": "il marchio"
  },
  {
    "german": "das Logo",
    "italian": "il logo"
  },
  {
    "german": "das Publikum",
    "italian": "il pubblico"
  },
  {
    "german": "die Anzeige",
    "italian": "l'annuncio"
  },
  {
    "german": "das Marketing",
    "italian": "il marketing"
  },
  {
    "german": "der Trend",
    "italian": "la tendenza"
  },
  {
    "german": "die Quelle",
    "italian": "la fonte"
  },
  {
    "german": "die Stirn",
    "italian": "la fronte"
  },
  {
    "german": "die Wange",
    "italian": "la guancia"
  },
  {
    "german": "die Lippe",
    "italian": "il labbro"
  },
  {
    "german": "das Kinn",
    "italian": "il mento"
  },
  {
    "german": "der Bart",
    "italian": "la barba"
  },
  {
    "german": "der Po",
    "italian": "il sedere"
  },
  {
    "german": "der Daumen",
    "italian": "il pollice"
  },
  {
    "german": "der Zeh",
    "italian": "il dito del piede"
  },
  {
    "german": "die Zehen",
    "italian": "le dita dei piedi"
  },
  {
    "german": "das Gehirn",
    "italian": "il cervello"
  },
  {
    "german": "das Blut",
    "italian": "il sangue"
  },
  {
    "german": "der Knochen",
    "italian": "l'osso"
  },
  {
    "german": "der Muskel",
    "italian": "il muscolo"
  },
  {
    "german": "die Haut",
    "italian": "la pelle"
  },
  {
    "german": "die Schmerzen",
    "italian": "i dolori"
  },
  {
    "german": "die Rückenschmerzen",
    "italian": "il mal di schiena"
  },
  {
    "german": "die Zahnschmerzen",
    "italian": "il mal di denti"
  },
  {
    "german": "die Halsschmerzen",
    "italian": "il mal di gola"
  },
  {
    "german": "die Grippe",
    "italian": "l'influenza"
  },
  {
    "german": "die Allergie",
    "italian": "l'allergia"
  },
  {
    "german": "die Müdigkeit",
    "italian": "la stanchezza"
  },
  {
    "german": "der Stress",
    "italian": "lo stress"
  },
  {
    "german": "die Angst",
    "italian": "l'ansia/la paura"
  },
  {
    "german": "das Virus",
    "italian": "il virus"
  },
  {
    "german": "die Wunde",
    "italian": "la ferita"
  },
  {
    "german": "die Verletzung",
    "italian": "la lesione"
  },
  {
    "german": "der Augenarzt",
    "italian": "l'oculista"
  },
  {
    "german": "der Kinderarzt",
    "italian": "il pediatra"
  },
  {
    "german": "die Krankenschwester",
    "italian": "l'infermiera"
  },
  {
    "german": "der Krankenpfleger",
    "italian": "l'infermiere"
  },
  {
    "german": "der Apotheker",
    "italian": "il farmacista"
  },
  {
    "german": "die Klinik",
    "italian": "la clinica"
  },
  {
    "german": "der Krankenwagen",
    "italian": "l'ambulanza"
  },
  {
    "german": "die Operation",
    "italian": "l'operazione"
  },
  {
    "german": "das Medikament",
    "italian": "il medicinale"
  },
  {
    "german": "die Tablette",
    "italian": "la compressa"
  },
  {
    "german": "die Spritze",
    "italian": "la siringa/l'iniezione"
  },
  {
    "german": "die Impfung",
    "italian": "la vaccinazione"
  },
  {
    "german": "das Pflaster",
    "italian": "il cerotto"
  },
  {
    "german": "der Patient",
    "italian": "il paziente"
  },
  {
    "german": "die Patientin",
    "italian": "la paziente"
  },
  {
    "german": "behandeln",
    "italian": "trattare"
  },
  {
    "german": "heilen",
    "italian": "guarire"
  },
  {
    "german": "verletzen",
    "italian": "ferire"
  },
  {
    "german": "bluten",
    "italian": "sanguinare"
  },
  {
    "german": "impfen",
    "italian": "vaccinare"
  },
  {
    "german": "einnehmen",
    "italian": "assumere"
  },
  {
    "german": "schlucken",
    "italian": "ingoiare"
  },
  {
    "german": "allergisch",
    "italian": "allergico"
  },
  {
    "german": "der Hausarzt",
    "italian": "il medico di base"
  },
  {
    "german": "operieren",
    "italian": "operare"
  },
  {
    "german": "der Blutdruck",
    "italian": "la pressione sanguigna"
  },
  {
    "german": "der Puls",
    "italian": "il polso"
  },
  {
    "german": "niesen",
    "italian": "starnutire"
  },
  {
    "german": "sich erkälten",
    "italian": "raffreddarsi"
  },
  {
    "german": "schmerzen",
    "italian": "far male"
  },
  {
    "german": "der Dokumentarfilm",
    "italian": "il documentario"
  },
  {
    "german": "der Animationsfilm",
    "italian": "il film d'animazione"
  },
  {
    "german": "der Zeichentrickfilm",
    "italian": "il cartone animato"
  },
  {
    "german": "der Thriller",
    "italian": "il thriller"
  },
  {
    "german": "der Horrorfilm",
    "italian": "il film horror"
  },
  {
    "german": "der Actionfilm",
    "italian": "il film d'azione"
  },
  {
    "german": "der Oscar",
    "italian": "l'Oscar"
  },
  {
    "german": "der Gewinn",
    "italian": "il profitto"
  },
  {
    "german": "der Verlust",
    "italian": "la perdita"
  },
  {
    "german": "die Ausgaben",
    "italian": "le spese"
  },
  {
    "german": "die Kosten",
    "italian": "i costi"
  },
  {
    "german": "die Währung",
    "italian": "la valuta"
  },
  {
    "german": "das Pfund",
    "italian": "la sterlina"
  }
]